README
setup.py
cmsplugin_section/__init__.py
cmsplugin_section/cms_plugins.py
cmsplugin_section/models.py
cmsplugin_section/tests.py
cmsplugin_section/utils.py
cmsplugin_section.egg-info/PKG-INFO
cmsplugin_section.egg-info/SOURCES.txt
cmsplugin_section.egg-info/dependency_links.txt
cmsplugin_section.egg-info/requires.txt
cmsplugin_section.egg-info/top_level.txt