Metadata-Version: 1.0
Name: cmsplugin-section
Version: 0.1.0
Summary: django-cms plugin for creating page sections with templates
Home-page: UNKNOWN
Author: Sasha Matijasic
Author-email: sasha@selectnull.com
License: LICENSE
Platform: UNKNOWN
